{
  "uuid": "0f7f0312d2a478f24e93aab47907fde6c1a3dd5e411bf98febe2322c67d803",
  "name": "AIOZ Network",
  "symbol": "AIOZ",
  "has_gas_sponsored": false,
  "is_stable_token": false,
  "wrapped_token_uuid": "",
  "logo_png_url": "https://s2.coinmarketcap.com/static/img/coins/64x64/9104.png",
  "logo_svg_url": "",
  "description": "AIOZ Network (AIOZ) is a cryptocurrency . AIOZ Network has a current supply of 1,210,458,341.71884076. The last known price of AIOZ Network is 0.19579569 USD and is down -9.22 over the last 24 hours. It is currently trading on 156 active market(s) with $15,086,420.55 traded over the last 24 hours. More information can be found at https://aioz.network/.",
  "coin_market_cap_id": 9104,
  "is_featured": false,
  "order_index": 3400,
  "website_url": "https://aioz.network/",
  "x_url": "https://twitter.com/AIOZNetwork",
  "discord_url": "",
  "whitepaper_url": "",
  "live_price_url": "",
  "tags": [],
  "is_scam": false,
  "is_disabled": false,
  "addresses": [
    {
      "address": "0x626e8036deb333b408be468f951bdb42433cbf18",
      "token_uid": "0f7f0312d2a478f24e93aab47907fde6c1a3dd5e411bf98febe2322c67d803",
      "network_id": 2,
      "is_verified": true,
      "decimals": 18,
      "is_native": false,
      "token_type": "ERC20",
      "upgradeable": false,
      "has_blue_checkmark": true,
      "gas_sponsored_strategy": 0,
      "name": "AIOZ Network",
      "symbol": "AIOZ",
      "logo_png_url": "https://s2.coinmarketcap.com/static/img/coins/64x64/9104.png",
      "logo_svg_url": ""
    },
    {
      "address": "0x33d08d8c7a168333a85285a68c0042b39fc3741d",
      "token_uid": "0f7f0312d2a478f24e93aab47907fde6c1a3dd5e411bf98febe2322c67d803",
      "network_id": 3,
      "is_verified": true,
      "decimals": 18,
      "is_native": false,
      "token_type": "ERC20",
      "upgradeable": false,
      "has_blue_checkmark": true,
      "gas_sponsored_strategy": 0,
      "name": "AIOZ Network",
      "symbol": "AIOZ",
      "logo_png_url": "https://s2.coinmarketcap.com/static/img/coins/64x64/9104.png",
      "logo_svg_url": ""
    }
  ]
}