{
  "uuid": "f825b183122984b1b7185cbd9eb0175175ee8bd14a8ff15805a323f7a009a7",
  "name": "TRON",
  "symbol": "TRX",
  "has_gas_sponsored": false,
  "is_stable_token": false,
  "wrapped_token_uuid": "",
  "logo_png_url": "https://s2.coinmarketcap.com/static/img/coins/64x64/1958.png",
  "logo_svg_url": "",
  "description": "TRON (TRX) is a cryptocurrency launched in 2018. TRON has a current supply of 94,663,698,987.710408 with 94,663,691,272.544708 in circulation. The last known price of TRON is 0.30919587 USD and is down -3.49 over the last 24 hours. It is currently trading on 1247 active market(s) with $1,282,353,330.87 traded over the last 24 hours. More information can be found at https://trondao.org/.",
  "coin_market_cap_id": 1958,
  "is_featured": true,
  "order_index": 160,
  "website_url": "https://trondao.org/",
  "x_url": "https://twitter.com/trondao",
  "discord_url": "",
  "whitepaper_url": "",
  "live_price_url": "",
  "tags": [],
  "is_scam": false,
  "is_disabled": false,
  "addresses": [
    {
      "address": "0x50327c6c5a14dcade707abad2e27eb517df87ab5",
      "token_uid": "f825b183122984b1b7185cbd9eb0175175ee8bd14a8ff15805a323f7a009a7",
      "network_id": 2,
      "is_verified": true,
      "decimals": 6,
      "is_native": false,
      "token_type": "ERC20",
      "upgradeable": false,
      "has_blue_checkmark": true,
      "gas_sponsored_strategy": 0,
      "name": "TRON",
      "symbol": "TRX",
      "logo_png_url": "https://s2.coinmarketcap.com/static/img/coins/64x64/1958.png",
      "logo_svg_url": ""
    },
    {
      "address": "0xce7de646e7208a4ef112cb6ed5038fa6cc6b12e3",
      "token_uid": "f825b183122984b1b7185cbd9eb0175175ee8bd14a8ff15805a323f7a009a7",
      "network_id": 3,
      "is_verified": true,
      "decimals": 6,
      "is_native": false,
      "token_type": "ERC20",
      "upgradeable": false,
      "has_blue_checkmark": true,
      "gas_sponsored_strategy": 0,
      "name": "TRON",
      "symbol": "TRX",
      "logo_png_url": "https://s2.coinmarketcap.com/static/img/coins/64x64/1958.png",
      "logo_svg_url": ""
    }
  ]
}